RangeHTTPServer/__init__.py
RangeHTTPServer/__main__.py
cellbrowser/__init__.py
cellbrowser/_version.py
cellbrowser/cellbrowser.py
cellbrowser/convert.py
cellbrowser/download.py
cellbrowser/geneinfo.py
cellbrowser/guessgenes.py
cellbrowser/hubmaker.py
cellbrowser/seurat.py
cellbrowser/R/ExportToCellbrowser-seurat.R
cellbrowser/cbWeb/css/cellBrowser.css
cellbrowser/cbWeb/ext/Chart.bundle.min.js
cellbrowser/cbWeb/ext/FastBitSet.js
cellbrowser/cbWeb/ext/FileSaver.1.1.20151003.min.js
cellbrowser/cbWeb/ext/OverlayScrollbars.min.css
cellbrowser/cbWeb/ext/bootstrap-dropmenu.min.css
cellbrowser/cbWeb/ext/bootstrap-submenu.js
cellbrowser/cbWeb/ext/bootstrap-submenu.min.css
cellbrowser/cbWeb/ext/bootstrap.3.3.7.min.css
cellbrowser/cbWeb/ext/bootstrap.min.css
cellbrowser/cbWeb/ext/bootstrap.min.js
cellbrowser/cbWeb/ext/chartjs-chart-box-and-violin-plot.js
cellbrowser/cbWeb/ext/chosen-sprite.png
cellbrowser/cbWeb/ext/chosen.1.8.2.min.css
cellbrowser/cbWeb/ext/chosen.jquery.min.js
cellbrowser/cbWeb/ext/font-awesome.css
cellbrowser/cbWeb/ext/googleMaterialIcons.css
cellbrowser/cbWeb/ext/hamster.js
cellbrowser/cbWeb/ext/intro.min.js
cellbrowser/cbWeb/ext/introjs.2.4.0.min.css
cellbrowser/cbWeb/ext/jquery-ui-1.12.1.css
cellbrowser/cbWeb/ext/jquery-ui.min.js
cellbrowser/cbWeb/ext/jquery.3.1.1.min.js
cellbrowser/cbWeb/ext/jquery.contextMenu.css
cellbrowser/cbWeb/ext/jquery.contextMenu.js
cellbrowser/cbWeb/ext/jquery.event.drag-2.3.0.js
cellbrowser/cbWeb/ext/jquery.overlayScrollbars.min.js
cellbrowser/cbWeb/ext/jquery.sparkline.min.js
cellbrowser/cbWeb/ext/jquery.tipsy.1.0.3.min.css
cellbrowser/cbWeb/ext/jquery.tipsy.min.js
cellbrowser/cbWeb/ext/jquery.ui.position.min.js
cellbrowser/cbWeb/ext/jsurl2.js
cellbrowser/cbWeb/ext/lz-string.js
cellbrowser/cbWeb/ext/materialIcons.woff
cellbrowser/cbWeb/ext/mousetrap.min.js
cellbrowser/cbWeb/ext/normalizeWheel.js
cellbrowser/cbWeb/ext/pako_inflate.min.js
cellbrowser/cbWeb/ext/palette.js
cellbrowser/cbWeb/ext/papaparse.min.js
cellbrowser-0.5.40.dist-info/LICENSE
cellbrowser-0.5.40.dist-info/METADATA
cellbrowser-0.5.40.dist-info/WHEEL
cellbrowser-0.5.40.dist-info/entry_points.txt
cellbrowser-0.5.40.dist-info/top_level.txt
cellbrowser-0.5.40.dist-info/RECORD
